[{"part":"Body","name":"New_Elf_1","color":"FFFFFFFF"},{"part":"Eyes","name":"Eye2","color":"CD0000FF"},{"part":"Hair_Helmet","name":"Elf_Helmet_12","color":"FFFFFFFF"},{"part":"Cloth","name":"Elf_Cloth_12","color":"FFFFFFFF"},{"part":"Pants","name":"Elf_Pant_14","color":"FFFFFFFF"},{"part":"Armor","name":"Elf_Armor_14","color":"FFFFFFFF"},{"part":"Back","name":"Elf_Back_07","color":"FFFFFFFF"},{"part":"Weapon_R","name":"Elf_Weapon_12","color":"FFFFFFFF"},{"part":"Weapon_L","name":"Shield_Sorceress","color":"FFFFFFFF"}]